pyepp/__init__.py
pyepp/base_command.py
pyepp/command_templates.py
pyepp/contact.py
pyepp/domain.py
pyepp/epp.py
pyepp/helper.py
pyepp/host.py
pyepp/poll.py
pyepp/cli/__init__.py
pyepp/cli/__main__.py
pyepp/cli/cli.py
pyepp/cli/contact.py
pyepp/cli/domain.py
pyepp/cli/host.py
pyepp/cli/poll.py
pyepp/cli/utils.py
pyepp-0.1.7.dist-info/licenses/LICENSE
pyepp-0.1.7.dist-info/METADATA
pyepp-0.1.7.dist-info/WHEEL
pyepp-0.1.7.dist-info/entry_points.txt
pyepp-0.1.7.dist-info/top_level.txt
pyepp-0.1.7.dist-info/RECORD
