Metadata-Version: 2.4
Name: pyepp
Version: 0.1.7
Summary: A Python API on top of the EPP protocol.
Author-email: InternetNZ <ehsan@internetnz.net.nz>
License-Expression: GPL-3.0-or-later
Project-URL: Homepage, https://github.com/InternetNZ/pyepp
Project-URL: Repository, https://github.com/InternetNZ/pyepp
Project-URL: Documentation, https://pyepp.readthedocs.io/en/latest/index.html
Keywords: epp,registry,api,domain,nameserver
Classifier: Programming Language :: Python
Classifier: Programming Language :: Python :: 3
Classifier: Programming Language :: Python :: 3.10
Classifier: Programming Language :: Python :: 3.11
Classifier: Programming Language :: Python :: 3.12
Classifier: Operating System :: OS Independent
Classifier: Intended Audience :: Developers
Classifier: Topic :: Internet :: Name Service (DNS)
Classifier: Topic :: Software Development :: Libraries :: Python Modules
Classifier: Topic :: Software Development :: Libraries :: Application Frameworks
Requires-Python: >=3.10
License-File: LICENSE
Requires-Dist: jinja2>=3.1.6
Requires-Dist: lxml>=5.4.0
Requires-Dist: beautifulsoup4>=4.13.4
Requires-Dist: click>=8.2.0
Provides-Extra: dev
Requires-Dist: bandit; extra == "dev"
Requires-Dist: coverage; extra == "dev"
Requires-Dist: pylint; extra == "dev"
Requires-Dist: pytest; extra == "dev"
Requires-Dist: safety; extra == "dev"
Dynamic: license-file
